fitsiochunked.py
fitsiochunked-0.2.1.dist-info/DESCRIPTION.rst
fitsiochunked-0.2.1.dist-info/METADATA
fitsiochunked-0.2.1.dist-info/metadata.json
fitsiochunked-0.2.1.dist-info/RECORD
fitsiochunked-0.2.1.dist-info/top_level.txt
fitsiochunked-0.2.1.dist-info/WHEEL
