Metadata-Version: 2.0
Name: fitsiochunked
Version: 0.2.1
Summary: Package to efficiently read large fits arrays in object by object
Home-page: https://github.com/mindriot101/fitsiochunked
Author: Simon Walker
Author-email: s.r.walker101@googlemail.com
License: MIT
Keywords: fitsiochunked
Platform: UNKNOWN
Classifier: Development Status :: 2 - Pre-Alpha
Classifier: Intended Audience :: Developers
Classifier: License :: OSI Approved :: MIT License
Classifier: Natural Language :: English
Classifier: Programming Language :: Python :: 2
Classifier: Programming Language :: Python :: 2.7
Classifier: Programming Language :: Python :: 3
Classifier: Programming Language :: Python :: 3.4
Classifier: Programming Language :: Python :: 3.5
Requires-Dist: fitsio
